tytg/__main__.py
tytg-0.2.7.2.dist-info/LICENSE
tytg-0.2.7.2.dist-info/METADATA
tytg-0.2.7.2.dist-info/WHEEL
tytg-0.2.7.2.dist-info/entry_points.txt
tytg-0.2.7.2.dist-info/top_level.txt
tytg-0.2.7.2.dist-info/RECORD
