Metadata-Version: 2.1
Name: tytg
Version: 0.2.7.2
Summary: Telegram bot making without any line of code.
Home-page: http://github.com/veggero/tytg
Author: veggero
Author-email: niccolo@venerandi.com
License: unlicenced
Platform: UNKNOWN
Requires-Dist: python-telegram-bot
